{
    "name": "Juan Pablo Tascón Roldan",
    "linkedin_url": "https://www.linkedin.com/in/juan-pablo-tascon-roldán-7b0698251/",
    "github_url": "https://github.com/juanpablotr14",
    "github_user": "juanpablotr14",
    "email": "juanpablotr14@gmail.com",
    "phone": "+573170647352",
    "location": "Cali, Valle del Cauca",
    "country": "Colombia",
    "neighborhood": "San Fernando",
    "x_username": "juanpablotr14",
    "website_url": "https://cayolegal.vercel.app",
    "location_url": "https://maps.app.goo.gl/t3Rd5A5RQ2kLSU9k9"
}